legacy_puyo_tools/__init__.py
legacy_puyo_tools/_math.py
legacy_puyo_tools/py.typed
legacy_puyo_tools/cli/__init__.py
legacy_puyo_tools/cli/confopts.py
legacy_puyo_tools/cli/convert.py
legacy_puyo_tools/cli/create.py
legacy_puyo_tools/formats/__init__.py
legacy_puyo_tools/formats/base.py
legacy_puyo_tools/formats/fmp.py
legacy_puyo_tools/formats/fpd.py
legacy_puyo_tools/formats/mtx.py
legacy_puyo_tools-2025.10.10.1.dist-info/METADATA
legacy_puyo_tools-2025.10.10.1.dist-info/WHEEL
legacy_puyo_tools-2025.10.10.1.dist-info/entry_points.txt
legacy_puyo_tools-2025.10.10.1.dist-info/licenses/LICENSE
legacy_puyo_tools-2025.10.10.1.dist-info/RECORD
