Metadata-Version: 2.4
Name: legacy-puyo-tools
Version: 2025.10.10.1
Summary: A tool to edit text for older Puyo Puyo games.
Project-URL: Changelog, https://github.com/wushenrong/legacy-puyo-tools/blob/main/CHANGELOG.md
Project-URL: Homepage, https://wushenrong.github.io/legacy-puyo-tools/
Project-URL: Issues, https://github.com/wushenrong/legacy-puyo-tools/issues
Project-URL: Source, https://github.com/wushenrong/legacy-puyo-tools.git
Author-email: Samuel Wu <twopizza9621536@gmail.com>
License-Expression: MIT
License-File: LICENSE
Keywords: puyopuyo
Classifier: Development Status :: 2 - Pre-Alpha
Classifier: Environment :: Console
Classifier: Intended Audience :: Other Audience
Classifier: License :: OSI Approved :: MIT License
Classifier: Operating System :: OS Independent
Classifier: Programming Language :: Python :: 3 :: Only
Classifier: Programming Language :: Python :: 3.12
Classifier: Programming Language :: Python :: 3.13
Classifier: Programming Language :: Python :: 3.14
Classifier: Topic :: File Formats
Classifier: Topic :: Games/Entertainment :: Puzzle Games
Classifier: Topic :: Utilities
Requires-Python: >=3.12
Requires-Dist: attrs>=25.3
Requires-Dist: bidict>=0.23.1
Requires-Dist: click>=8.2.1
Requires-Dist: cloup>=3.0.7
Requires-Dist: lxml>=6
Requires-Dist: numpy>=2.0.2
Requires-Dist: pillow>=11.3
